[
  {
    "ContainingType": "todolistProject.API.Controllers.GroupController",
    "Method": "GetGroups",
    "RelativePath": "api/Group",
    "HttpMethod": "GET",
    "IsController": true,
    "Order": 0,
    "Parameters": [],
    "ReturnTypes": [
      {
        "Type": "System.Collections.Generic.List\u00601[[todolistProject.API.Contracts.GroupsResponse, todolistProject.API, Version=1.0.0.0, Culture=neutral, PublicKeyToken=null]]",
        "MediaTypes": [
          "text/plain",
          "application/json",
          "text/json"
        ],
        "StatusCode": 200
      }
    ]
  },
  {
    "ContainingType": "todolistProject.API.Controllers.GroupController",
    "Method": "CreateGroup",
    "RelativePath": "api/Group",
    "HttpMethod": "POST",
    "IsController": true,
    "Order": 0,
    "Parameters": [
      {
        "Name": "request",
        "Type": "todolistProject.API.Contracts.GroupsRequest",
        "IsRequired": true
      }
    ],
    "ReturnTypes": [
      {
        "Type": "System.Guid",
        "MediaTypes": [
          "text/plain",
          "application/json",
          "text/json"
        ],
        "StatusCode": 200
      }
    ]
  },
  {
    "ContainingType": "todolistProject.API.Controllers.GroupController",
    "Method": "UpdateGroup",
    "RelativePath": "api/Group/{idGroup}",
    "HttpMethod": "PUT",
    "IsController": true,
    "Order": 0,
    "Parameters": [
      {
        "Name": "idGroup",
        "Type": "System.Guid",
        "IsRequired": true
      },
      {
        "Name": "request",
        "Type": "todolistProject.API.Contracts.GroupsRequest",
        "IsRequired": true
      }
    ],
    "ReturnTypes": [
      {
        "Type": "System.Guid",
        "MediaTypes": [
          "text/plain",
          "application/json",
          "text/json"
        ],
        "StatusCode": 200
      }
    ]
  },
  {
    "ContainingType": "todolistProject.API.Controllers.GroupController",
    "Method": "DeleteGroup",
    "RelativePath": "api/Group/{idGroup}",
    "HttpMethod": "DELETE",
    "IsController": true,
    "Order": 0,
    "Parameters": [
      {
        "Name": "idGroup",
        "Type": "System.Guid",
        "IsRequired": true
      }
    ],
    "ReturnTypes": [
      {
        "Type": "System.Guid",
        "MediaTypes": [
          "text/plain",
          "application/json",
          "text/json"
        ],
        "StatusCode": 200
      }
    ]
  },
  {
    "ContainingType": "todolistProject.API.Controllers.GroupController",
    "Method": "GetGroupById",
    "RelativePath": "api/Group/ById/{groupId}",
    "HttpMethod": "GET",
    "IsController": true,
    "Order": 0,
    "Parameters": [
      {
        "Name": "groupId",
        "Type": "System.Guid",
        "IsRequired": true
      }
    ],
    "ReturnTypes": [
      {
        "Type": "todolistProject.Core.Models.Group",
        "MediaTypes": [
          "text/plain",
          "application/json",
          "text/json"
        ],
        "StatusCode": 200
      }
    ]
  },
  {
    "ContainingType": "todolistProject.API.Controllers.GroupController",
    "Method": "GetGroupByUserId",
    "RelativePath": "api/Group/ByUserId/{userId}",
    "HttpMethod": "GET",
    "IsController": true,
    "Order": 0,
    "Parameters": [
      {
        "Name": "userId",
        "Type": "System.Guid",
        "IsRequired": true
      }
    ],
    "ReturnTypes": [
      {
        "Type": "System.Collections.Generic.List\u00601[[todolistProject.Core.Models.Group, todolistProject.Core, Version=1.0.0.0, Culture=neutral, PublicKeyToken=null]]",
        "MediaTypes": [
          "text/plain",
          "application/json",
          "text/json"
        ],
        "StatusCode": 200
      }
    ]
  },
  {
    "ContainingType": "todolistProject.API.Controllers.NoteController",
    "Method": "GetNotes",
    "RelativePath": "api/Note",
    "HttpMethod": "GET",
    "IsController": true,
    "Order": 0,
    "Parameters": [],
    "ReturnTypes": [
      {
        "Type": "System.Collections.Generic.List\u00601[[todolistProject.API.Contracts.NotesResponse, todolistProject.API, Version=1.0.0.0, Culture=neutral, PublicKeyToken=null]]",
        "MediaTypes": [
          "text/plain",
          "application/json",
          "text/json"
        ],
        "StatusCode": 200
      }
    ]
  },
  {
    "ContainingType": "todolistProject.API.Controllers.NoteController",
    "Method": "CreateNote",
    "RelativePath": "api/Note",
    "HttpMethod": "POST",
    "IsController": true,
    "Order": 0,
    "Parameters": [
      {
        "Name": "request",
        "Type": "todolistProject.API.Contracts.NotesRequest",
        "IsRequired": true
      }
    ],
    "ReturnTypes": [
      {
        "Type": "System.Guid",
        "MediaTypes": [
          "text/plain",
          "application/json",
          "text/json"
        ],
        "StatusCode": 200
      }
    ]
  },
  {
    "ContainingType": "todolistProject.API.Controllers.NoteController",
    "Method": "UpdateTitleNote",
    "RelativePath": "api/Note/{idNote}",
    "HttpMethod": "PUT",
    "IsController": true,
    "Order": 0,
    "Parameters": [
      {
        "Name": "idNote",
        "Type": "System.Guid",
        "IsRequired": true
      },
      {
        "Name": "request",
        "Type": "todolistProject.API.Contracts.NotesTitleRequest",
        "IsRequired": true
      }
    ],
    "ReturnTypes": [
      {
        "Type": "System.Guid",
        "MediaTypes": [
          "text/plain",
          "application/json",
          "text/json"
        ],
        "StatusCode": 200
      }
    ]
  },
  {
    "ContainingType": "todolistProject.API.Controllers.NoteController",
    "Method": "DeleteNote",
    "RelativePath": "api/Note/{idNote}",
    "HttpMethod": "DELETE",
    "IsController": true,
    "Order": 0,
    "Parameters": [
      {
        "Name": "idNote",
        "Type": "System.Guid",
        "IsRequired": true
      }
    ],
    "ReturnTypes": [
      {
        "Type": "System.Guid",
        "MediaTypes": [
          "text/plain",
          "application/json",
          "text/json"
        ],
        "StatusCode": 200
      }
    ]
  },
  {
    "ContainingType": "todolistProject.API.Controllers.NoteController",
    "Method": "GetNoteById",
    "RelativePath": "api/Note/ById/{idNote}",
    "HttpMethod": "GET",
    "IsController": true,
    "Order": 0,
    "Parameters": [
      {
        "Name": "idNote",
        "Type": "System.Guid",
        "IsRequired": true
      }
    ],
    "ReturnTypes": [
      {
        "Type": "todolistProject.API.Contracts.NotesResponse",
        "MediaTypes": [
          "text/plain",
          "application/json",
          "text/json"
        ],
        "StatusCode": 200
      }
    ]
  },
  {
    "ContainingType": "todolistProject.API.Controllers.NoteController",
    "Method": "GetNoteByUserId",
    "RelativePath": "api/Note/ByUserId/{idUser}",
    "HttpMethod": "GET",
    "IsController": true,
    "Order": 0,
    "Parameters": [
      {
        "Name": "idUser",
        "Type": "System.Guid",
        "IsRequired": true
      }
    ],
    "ReturnTypes": [
      {
        "Type": "System.Collections.Generic.List\u00601[[todolistProject.Core.Models.Note, todolistProject.Core, Version=1.0.0.0, Culture=neutral, PublicKeyToken=null]]",
        "MediaTypes": [
          "text/plain",
          "application/json",
          "text/json"
        ],
        "StatusCode": 200
      }
    ]
  },
  {
    "ContainingType": "todolistProject.API.Controllers.NoteController",
    "Method": "SaveNoteContext",
    "RelativePath": "api/Note/Content/{idNote}",
    "HttpMethod": "PUT",
    "IsController": true,
    "Order": 0,
    "Parameters": [
      {
        "Name": "idNote",
        "Type": "System.Guid",
        "IsRequired": true
      },
      {
        "Name": "request",
        "Type": "todolistProject.API.Contracts.NotesContentRequest",
        "IsRequired": true
      }
    ],
    "ReturnTypes": [
      {
        "Type": "System.Guid",
        "MediaTypes": [
          "text/plain",
          "application/json",
          "text/json"
        ],
        "StatusCode": 200
      }
    ]
  },
  {
    "ContainingType": "todolistProject.API.Controllers.UserController",
    "Method": "GetNotes",
    "RelativePath": "api/User",
    "HttpMethod": "GET",
    "IsController": true,
    "Order": 0,
    "Parameters": [],
    "ReturnTypes": [
      {
        "Type": "System.Collections.Generic.List\u00601[[todolistProject.API.Contracts.UsersResponse, todolistProject.API, Version=1.0.0.0, Culture=neutral, PublicKeyToken=null]]",
        "MediaTypes": [
          "text/plain",
          "application/json",
          "text/json"
        ],
        "StatusCode": 200
      }
    ]
  },
  {
    "ContainingType": "todolistProject.API.Controllers.UserController",
    "Method": "CreateUser",
    "RelativePath": "api/User",
    "HttpMethod": "POST",
    "IsController": true,
    "Order": 0,
    "Parameters": [
      {
        "Name": "request",
        "Type": "todolistProject.API.Contracts.UsersRequest",
        "IsRequired": true
      }
    ],
    "ReturnTypes": [
      {
        "Type": "System.Guid",
        "MediaTypes": [
          "text/plain",
          "application/json",
          "text/json"
        ],
        "StatusCode": 200
      }
    ]
  },
  {
    "ContainingType": "todolistProject.API.Controllers.UserController",
    "Method": "UpdateUser",
    "RelativePath": "api/User/{userid}",
    "HttpMethod": "PUT",
    "IsController": true,
    "Order": 0,
    "Parameters": [
      {
        "Name": "userid",
        "Type": "System.Guid",
        "IsRequired": true
      },
      {
        "Name": "request",
        "Type": "todolistProject.API.Contracts.UsersRequest",
        "IsRequired": true
      }
    ],
    "ReturnTypes": [
      {
        "Type": "System.Guid",
        "MediaTypes": [
          "text/plain",
          "application/json",
          "text/json"
        ],
        "StatusCode": 200
      }
    ]
  },
  {
    "ContainingType": "todolistProject.API.Controllers.UserController",
    "Method": "DeleteUser",
    "RelativePath": "api/User/{userid}",
    "HttpMethod": "DELETE",
    "IsController": true,
    "Order": 0,
    "Parameters": [
      {
        "Name": "userid",
        "Type": "System.Guid",
        "IsRequired": true
      }
    ],
    "ReturnTypes": [
      {
        "Type": "System.Guid",
        "MediaTypes": [
          "text/plain",
          "application/json",
          "text/json"
        ],
        "StatusCode": 200
      }
    ]
  },
  {
    "ContainingType": "todolistProject.API.Controllers.UserController",
    "Method": "GetUserById",
    "RelativePath": "api/User/ById/{userId}",
    "HttpMethod": "GET",
    "IsController": true,
    "Order": 0,
    "Parameters": [
      {
        "Name": "userId",
        "Type": "System.Guid",
        "IsRequired": true
      }
    ],
    "ReturnTypes": [
      {
        "Type": "todolistProject.API.Contracts.UsersResponse",
        "MediaTypes": [
          "text/plain",
          "application/json",
          "text/json"
        ],
        "StatusCode": 200
      }
    ]
  }
]